optimal_loc/Modelling Algorithm.png
optimal_loc/__init__.py
optimal_loc/app.py
optimal_loc/app_constants.py
optimal_loc/bash_command.py
optimal_loc/st_app.py
optimal_loc-0.1.7.dist-info/LICENSE
optimal_loc-0.1.7.dist-info/METADATA
optimal_loc-0.1.7.dist-info/WHEEL
optimal_loc-0.1.7.dist-info/RECORD
